mxos/__init__.py
mxos/mxos.py
mxos_cube-0.1.0.dist-info/DESCRIPTION.rst
mxos_cube-0.1.0.dist-info/METADATA
mxos_cube-0.1.0.dist-info/RECORD
mxos_cube-0.1.0.dist-info/WHEEL
mxos_cube-0.1.0.dist-info/entry_points.txt
mxos_cube-0.1.0.dist-info/metadata.json
mxos_cube-0.1.0.dist-info/top_level.txt
