Metadata-Version: 2.0
Name: mxos-cube
Version: 0.1.0
Summary: MXCHIP MXOS command line tool for repositories version control, publishing and updating code from remotely hosted repositories, and invoking MXOS own build system and export functions, among other operations
Home-page: https://github.com/MXCHIP/mxos-cube
Author: MXCHIP
Author-email: yangsw@mxchip.com
License: UNKNOWN
Platform: UNKNOWN
Classifier: Programming Language :: Python :: 2
Classifier: Programming Language :: Python :: 3
Classifier: License :: OSI Approved :: Apache Software License
Classifier: Operating System :: OS Independent
Requires-Python: >=2.7.10,!=3.0.*,!=3.1.*,<4
